{
  "buildCommand" : {
    "command" : "build",
    "skipDependencies" : false,
    "style" : "buildAndRun"
  },
  "configuredTargets" : [
    {
      "guid" : "8801a35858118bd90ff1dfadd67ac0d8a0ac817c5fc880a7a1a2eca53f125eb9"
    }
  ],
  "containerPath" : "/Users/YashB/Seaus/FreeUp/FreeUp/FreeUp.xcodeproj",
  "continueBuildingAfterErrors" : false,
  "dependencyScope" : "workspace",
  "enableIndexBuildArena" : false,
  "hideShellScriptEnvironment" : false,
  "parameters" : {
    "action" : "build",
    "overrides" : {
      "commandLine" : {
        "table" : {

        }
      },
      "synthesized" : {
        "table" : {
          "ACTION" : "build",
          "COLOR_DIAGNOSTICS" : "YES",
          "diagnostic_message_length" : "120",
          "ENABLE_PREVIEWS" : "NO",
          "ENABLE_XOJIT_PREVIEWS" : "NO"
        }
      }
    }
  },
  "showNonLoggedProgress" : true,
  "useDryRun" : false,
  "useImplicitDependencies" : false,
  "useLegacyBuildLocations" : false,
  "useParallelTargets" : true
}